{
  "data": {
    "mal_id": 1883,
    "url": "https://myanimelist.net/anime/1883/Kappa_no_Kaikata",
    "images": {
      "jpg": {
        "image_url": "https://cdn.myanimelist.net/images/anime/1827/99134.jpg",
        "small_image_url": "https://cdn.myanimelist.net/images/anime/1827/99134t.jpg",
        "large_image_url": "https://cdn.myanimelist.net/images/anime/1827/99134l.jpg"
      },
      "webp": {
        "image_url": "https://cdn.myanimelist.net/images/anime/1827/99134.webp",
        "small_image_url": "https://cdn.myanimelist.net/images/anime/1827/99134t.webp",
        "large_image_url": "https://cdn.myanimelist.net/images/anime/1827/99134l.webp"
      }
    },
    "trailer": {
      "youtube_id": null,
      "url": null,
      "embed_url": null,
      "images": {
        "image_url": null,
        "small_image_url": null,
        "medium_image_url": null,
        "large_image_url": null,
        "maximum_image_url": null
      }
    },
    "approved": true,
    "titles": [
      {
        "type": "Default",
        "title": "Kappa no Kaikata"
      },
      {
        "type": "Synonym",
        "title": "Kappa no Kai-kata"
      },
      {
        "type": "Synonym",
        "title": "How to Raise a Water Imp"
      },
      {
        "type": "Japanese",
        "title": "カッパの飼い方"
      },
      {
        "type": "English",
        "title": "How to Breed Kappas"
      }
    ],
    "title": "Kappa no Kaikata",
    "title_english": "How to Breed Kappas",
    "title_japanese": "カッパの飼い方",
    "title_synonyms": [
      "Kappa no Kai-kata",
      "How to Raise a Water Imp"
    ],
    "type": "TV",
    "source": "Manga",
    "episodes": 26,
    "status": "Finished Airing",
    "airing": false,
    "aired": {
      "from": "2004-10-04T00:00:00+00:00",
      "to": "2005-04-04T00:00:00+00:00",
      "prop": {
        "from": {
          "day": 4,
          "month": 10,
          "year": 2004
        },
        "to": {
          "day": 4,
          "month": 4,
          "year": 2005
        }
      },
      "string": "Oct 4, 2004 to Apr 4, 2005"
    },
    "duration": "3 min per ep",
    "rating": "PG - Children",
    "score": 6.2,
    "scored_by": 930,
    "rank": 8827,
    "popularity": 11209,
    "members": 2410,
    "favorites": 4,
    "synopsis": "A young man passes a pet shop on his way home, and seeing a kappa in the window, decides to buy it on a whim. He brings the creature home, and names him Kaatan. He's never owned a kappa before, so he relies heavily on a book he purchased on the subject of raising and training kappa. The books gives several good tips for bringing up a smart and well behaved kappa, and it all seems very simple. Unfortunately, putting these techniques into practice and actually making them work is not quite as easy as the book implies. Kaatan seems to understand things at first, but usually ends up either forgetting what he's learned, or isn't interested in learning in the first place. However, this particular young man has a lot of patience, and continues his possibly fruitless effort to raise Kaatan into a pet he can be proud of.\n\n(Source: ANN)",
    "background": "",
    "season": "fall",
    "year": 2004,
    "broadcast": {
      "day": null,
      "time": null,
      "timezone": null,
      "string": "Unknown"
    },
    "producers": [
      {
        "mal_id": 139,
        "type": "anime",
        "name": "Nihon Ad Systems",
        "url": "https://myanimelist.net/anime/producer/139/Nihon_Ad_Systems"
      }
    ],
    "licensors": [],
    "studios": [
      {
        "mal_id": 78,
        "type": "anime",
        "name": "Picture Magic",
        "url": "https://myanimelist.net/anime/producer/78/Picture_Magic"
      }
    ],
    "genres": [
      {
        "mal_id": 4,
        "type": "anime",
        "name": "Comedy",
        "url": "https://myanimelist.net/anime/genre/4/Comedy"
      }
    ],
    "explicit_genres": [],
    "themes": [
      {
        "mal_id": 71,
        "type": "anime",
        "name": "Pets",
        "url": "https://myanimelist.net/anime/genre/71/Pets"
      }
    ],
    "demographics": [],
    "relations": [
      {
        "relation": "Adaptation",
        "entry": [
          {
            "mal_id": 106890,
            "type": "manga",
            "name": "Kappa no Kaikata",
            "url": "https://myanimelist.net/manga/106890/Kappa_no_Kaikata"
          }
        ]
      }
    ],
    "theme": {
      "openings": [
        "\"Brilliant Destiny\" by Murata Ayumi"
      ],
      "endings": []
    },
    "external": [
      {
        "name": "AniDB",
        "url": "https://anidb.net/perl-bin/animedb.pl?show=anime&aid=2340"
      },
      {
        "name": "ANN",
        "url": "https://www.animenewsnetwork.com/encyclopedia/anime.php?id=4492"
      },
      {
        "name": "Wikipedia",
        "url": "https://en.wikipedia.org/wiki/Kappa_no_Kaikata"
      }
    ],
    "streaming": []
  }
}