{
  "data": {
    "mal_id": 2213,
    "url": "https://myanimelist.net/anime/2213/Black_Jack_TV",
    "images": {
      "jpg": {
        "image_url": "https://cdn.myanimelist.net/images/anime/1588/133791.jpg",
        "small_image_url": "https://cdn.myanimelist.net/images/anime/1588/133791t.jpg",
        "large_image_url": "https://cdn.myanimelist.net/images/anime/1588/133791l.jpg"
      },
      "webp": {
        "image_url": "https://cdn.myanimelist.net/images/anime/1588/133791.webp",
        "small_image_url": "https://cdn.myanimelist.net/images/anime/1588/133791t.webp",
        "large_image_url": "https://cdn.myanimelist.net/images/anime/1588/133791l.webp"
      }
    },
    "trailer": {
      "youtube_id": null,
      "url": null,
      "embed_url": null,
      "images": {
        "image_url": null,
        "small_image_url": null,
        "medium_image_url": null,
        "large_image_url": null,
        "maximum_image_url": null
      }
    },
    "approved": true,
    "titles": [
      {
        "type": "Default",
        "title": "Black Jack (TV)"
      },
      {
        "type": "Synonym",
        "title": "Black Jack 2004"
      },
      {
        "type": "Japanese",
        "title": "ブラックジャック"
      },
      {
        "type": "Spanish",
        "title": "Black Jack"
      },
      {
        "type": "French",
        "title": "Black Jack"
      }
    ],
    "title": "Black Jack (TV)",
    "title_english": null,
    "title_japanese": "ブラックジャック",
    "title_synonyms": [
      "Black Jack 2004"
    ],
    "type": "TV",
    "source": "Manga",
    "episodes": 61,
    "status": "Finished Airing",
    "airing": false,
    "aired": {
      "from": "2004-10-11T00:00:00+00:00",
      "to": "2006-03-06T00:00:00+00:00",
      "prop": {
        "from": {
          "day": 11,
          "month": 10,
          "year": 2004
        },
        "to": {
          "day": 6,
          "month": 3,
          "year": 2006
        }
      },
      "string": "Oct 11, 2004 to Mar 6, 2006"
    },
    "duration": "25 min per ep",
    "rating": "PG-13 - Teens 13 or older",
    "score": 7.58,
    "scored_by": 13191,
    "rank": 1632,
    "popularity": 3809,
    "members": 38133,
    "favorites": 211,
    "synopsis": "Black Jack is an \"unregistered\" doctor with a clouded, mysterious past. He works with his little assistant Pinoko (who has a massive crush on the doctor), dealing with medical cases not very well known, which can be strange, dangerous, or not known at all. But he is a genius, and can save almost any of his patients' life (as long as they have the money for it, that is), and is known to many around the world, especially to those of medicine and science. He's a man of science himself, and does not believe much until he has seen it, yet it is many times he is surprised by love and nature often overpowering the science he bases his life in.  \n\n(Source: ANN)",
    "background": "",
    "season": "fall",
    "year": 2004,
    "broadcast": {
      "day": "Mondays",
      "time": "19:00",
      "timezone": "Asia/Tokyo",
      "string": "Mondays at 19:00 (JST)"
    },
    "producers": [
      {
        "mal_id": 76,
        "type": "anime",
        "name": "Yomiuri Telecasting",
        "url": "https://myanimelist.net/anime/producer/76/Yomiuri_Telecasting"
      }
    ],
    "licensors": [],
    "studios": [
      {
        "mal_id": 200,
        "type": "anime",
        "name": "Tezuka Productions",
        "url": "https://myanimelist.net/anime/producer/200/Tezuka_Productions"
      }
    ],
    "genres": [
      {
        "mal_id": 8,
        "type": "anime",
        "name": "Drama",
        "url": "https://myanimelist.net/anime/genre/8/Drama"
      }
    ],
    "explicit_genres": [],
    "themes": [
      {
        "mal_id": 67,
        "type": "anime",
        "name": "Medical",
        "url": "https://myanimelist.net/anime/genre/67/Medical"
      }
    ],
    "demographics": [
      {
        "mal_id": 27,
        "type": "anime",
        "name": "Shounen",
        "url": "https://myanimelist.net/anime/genre/27/Shounen"
      }
    ],
    "relations": [
      {
        "relation": "Prequel",
        "entry": [
          {
            "mal_id": 1373,
            "type": "anime",
            "name": "Black Jack Specials: Inochi wo Meguru Yottsu no Kiseki",
            "url": "https://myanimelist.net/anime/1373/Black_Jack_Specials__Inochi_wo_Meguru_Yottsu_no_Kiseki"
          }
        ]
      },
      {
        "relation": "Sequel",
        "entry": [
          {
            "mal_id": 2214,
            "type": "anime",
            "name": "Black Jack 21",
            "url": "https://myanimelist.net/anime/2214/Black_Jack_21"
          }
        ]
      },
      {
        "relation": "Adaptation",
        "entry": [
          {
            "mal_id": 1600,
            "type": "manga",
            "name": "Black Jack",
            "url": "https://myanimelist.net/manga/1600/Black_Jack"
          }
        ]
      },
      {
        "relation": "Side Story",
        "entry": [
          {
            "mal_id": 4070,
            "type": "anime",
            "name": "Black Jack: Dr. Pinoko no Mori no Bouken",
            "url": "https://myanimelist.net/anime/4070/Black_Jack__Dr_Pinoko_no_Mori_no_Bouken"
          },
          {
            "mal_id": 1983,
            "type": "anime",
            "name": "Black Jack: Futari no Kuroi Isha",
            "url": "https://myanimelist.net/anime/1983/Black_Jack__Futari_no_Kuroi_Isha"
          },
          {
            "mal_id": 4071,
            "type": "anime",
            "name": "Black Jack (TV): Hizouban Specials",
            "url": "https://myanimelist.net/anime/4071/Black_Jack_TV__Hizouban_Specials"
          }
        ]
      },
      {
        "relation": "Spin-Off",
        "entry": [
          {
            "mal_id": 919,
            "type": "anime",
            "name": "Ray The Animation",
            "url": "https://myanimelist.net/anime/919/Ray_The_Animation"
          }
        ]
      },
      {
        "relation": "Alternative Version",
        "entry": [
          {
            "mal_id": 1520,
            "type": "anime",
            "name": "Black Jack",
            "url": "https://myanimelist.net/anime/1520/Black_Jack"
          },
          {
            "mal_id": 7229,
            "type": "anime",
            "name": "Black Jack ONA",
            "url": "https://myanimelist.net/anime/7229/Black_Jack_ONA"
          }
        ]
      },
      {
        "relation": "Other",
        "entry": [
          {
            "mal_id": 18669,
            "type": "anime",
            "name": "Black Jack: Karte NG Extras",
            "url": "https://myanimelist.net/anime/18669/Black_Jack__Karte_NG_Extras"
          }
        ]
      }
    ],
    "theme": {
      "openings": [
        "1: \"Gekkouka (月光花)\" by Janne Da Arc (eps 1-28)",
        "2: \"Here I Am\" by globe (eps 29-51)",
        "3: \"Fantastic\" by Ami Suzuki (eps 52-61)"
      ],
      "endings": [
        "1: \"Kuroge Wagyuu Kamishio Tanyaki 680 En (黒毛和牛上塩タン焼680円)\" by Ai Ootsuka (eps 1-28)",
        "2: \"Clover\" by hiro (eps 29-51)",
        "3: \"Careless Breath\" by EXILE (eps 52-61)"
      ]
    },
    "external": [
      {
        "name": "Official Site",
        "url": "http://www.ytv.co.jp/bj/"
      },
      {
        "name": "AniDB",
        "url": "https://anidb.net/perl-bin/animedb.pl?show=anime&aid=2389"
      },
      {
        "name": "ANN",
        "url": "https://www.animenewsnetwork.com/encyclopedia/anime.php?id=4408"
      },
      {
        "name": "Wikipedia",
        "url": "http://en.wikipedia.org/wiki/Black_Jack_(manga)"
      }
    ],
    "streaming": [
      {
        "name": "Crunchyroll",
        "url": "http://www.crunchyroll.com/series-52948"
      },
      {
        "name": "Shahid",
        "url": "https://shahid.mbc.net/en/series/Black-Jack/series-913754"
      },
      {
        "name": "Tubi TV",
        "url": "https://tubitv.com/series/4135/black-jack"
      }
    ]
  }
}