{
  "data": {
    "mal_id": 28765,
    "url": "https://myanimelist.net/anime/28765/The_Baby_Birds_of_Norman_McLaren",
    "images": {
      "jpg": {
        "image_url": "https://cdn.myanimelist.net/images/anime/2/73404.jpg",
        "small_image_url": "https://cdn.myanimelist.net/images/anime/2/73404t.jpg",
        "large_image_url": "https://cdn.myanimelist.net/images/anime/2/73404l.jpg"
      },
      "webp": {
        "image_url": "https://cdn.myanimelist.net/images/anime/2/73404.webp",
        "small_image_url": "https://cdn.myanimelist.net/images/anime/2/73404t.webp",
        "large_image_url": "https://cdn.myanimelist.net/images/anime/2/73404l.webp"
      }
    },
    "trailer": {
      "youtube_id": null,
      "url": null,
      "embed_url": null,
      "images": {
        "image_url": null,
        "small_image_url": null,
        "medium_image_url": null,
        "large_image_url": null,
        "maximum_image_url": null
      }
    },
    "approved": true,
    "titles": [
      {
        "type": "Default",
        "title": "The Baby Birds of Norman McLaren"
      },
      {
        "type": "Japanese",
        "title": "The Baby Birds of Norman McLaren"
      }
    ],
    "title": "The Baby Birds of Norman McLaren",
    "title_english": null,
    "title_japanese": "The Baby Birds of Norman McLaren",
    "title_synonyms": [],
    "type": "Movie",
    "source": "Music",
    "episodes": 1,
    "status": "Finished Airing",
    "airing": false,
    "aired": {
      "from": "2014-01-01T00:00:00+00:00",
      "to": null,
      "prop": {
        "from": {
          "day": 1,
          "month": 1,
          "year": 2014
        },
        "to": {
          "day": null,
          "month": null,
          "year": null
        }
      },
      "string": "2014"
    },
    "duration": "3 min",
    "rating": "G - All Ages",
    "score": 5.32,
    "scored_by": 376,
    "rank": 12585,
    "popularity": 15415,
    "members": 697,
    "favorites": 1,
    "synopsis": "Celebrating the 100th year of birth of Norman McLaren, this short animation is set to the song \"Poker\" by Shugo Tokumaru and is the \"sister piece\" to its music video, also animated by Mirai Mizue and Yukie Tanauchi. It was made as part of the NFB \"Wall-to-Wall\" contest.",
    "background": "",
    "season": null,
    "year": null,
    "broadcast": {
      "day": null,
      "time": null,
      "timezone": null,
      "string": null
    },
    "producers": [],
    "licensors": [],
    "studios": [
      {
        "mal_id": 1249,
        "type": "anime",
        "name": "Mirai Film",
        "url": "https://myanimelist.net/anime/producer/1249/Mirai_Film"
      }
    ],
    "genres": [],
    "explicit_genres": [],
    "themes": [
      {
        "mal_id": 19,
        "type": "anime",
        "name": "Music",
        "url": "https://myanimelist.net/anime/genre/19/Music"
      }
    ],
    "demographics": [],
    "relations": [
      {
        "relation": "Alternative Version",
        "entry": [
          {
            "mal_id": 28687,
            "type": "anime",
            "name": "Poker",
            "url": "https://myanimelist.net/anime/28687/Poker"
          }
        ]
      },
      {
        "relation": "Other",
        "entry": [
          {
            "mal_id": 29311,
            "type": "anime",
            "name": "Shousei Shikisai Gensou",
            "url": "https://myanimelist.net/anime/29311/Shousei_Shikisai_Gensou"
          }
        ]
      }
    ],
    "theme": {
      "openings": [],
      "endings": []
    },
    "external": [
      {
        "name": "Official Site",
        "url": "http://www.fidff.com/com/2014-i15.html"
      }
    ],
    "streaming": []
  }
}