{
  "data": {
    "mal_id": 31236,
    "url": "https://myanimelist.net/anime/31236/Chieri_to_Cherry",
    "images": {
      "jpg": {
        "image_url": "https://cdn.myanimelist.net/images/anime/5/78815.jpg",
        "small_image_url": "https://cdn.myanimelist.net/images/anime/5/78815t.jpg",
        "large_image_url": "https://cdn.myanimelist.net/images/anime/5/78815l.jpg"
      },
      "webp": {
        "image_url": "https://cdn.myanimelist.net/images/anime/5/78815.webp",
        "small_image_url": "https://cdn.myanimelist.net/images/anime/5/78815t.webp",
        "large_image_url": "https://cdn.myanimelist.net/images/anime/5/78815l.webp"
      }
    },
    "trailer": {
      "youtube_id": "onNtwAfRoCE",
      "url": "https://www.youtube.com/watch?v=onNtwAfRoCE",
      "embed_url": "https://www.youtube.com/embed/onNtwAfRoCE?enablejsapi=1&wmode=opaque&autoplay=1",
      "images": {
        "image_url": "https://img.youtube.com/vi/onNtwAfRoCE/default.jpg",
        "small_image_url": "https://img.youtube.com/vi/onNtwAfRoCE/sddefault.jpg",
        "medium_image_url": "https://img.youtube.com/vi/onNtwAfRoCE/mqdefault.jpg",
        "large_image_url": "https://img.youtube.com/vi/onNtwAfRoCE/hqdefault.jpg",
        "maximum_image_url": "https://img.youtube.com/vi/onNtwAfRoCE/maxresdefault.jpg"
      }
    },
    "approved": true,
    "titles": [
      {
        "type": "Default",
        "title": "Chieri to Cherry"
      },
      {
        "type": "Japanese",
        "title": "ちえりとチェリー"
      },
      {
        "type": "English",
        "title": "Chieri and Cherry"
      }
    ],
    "title": "Chieri to Cherry",
    "title_english": "Chieri and Cherry",
    "title_japanese": "ちえりとチェリー",
    "title_synonyms": [],
    "type": "Movie",
    "source": "Original",
    "episodes": 1,
    "status": "Finished Airing",
    "airing": false,
    "aired": {
      "from": "2016-02-20T00:00:00+00:00",
      "to": null,
      "prop": {
        "from": {
          "day": 20,
          "month": 2,
          "year": 2016
        },
        "to": {
          "day": null,
          "month": null,
          "year": null
        }
      },
      "string": "Feb 20, 2016"
    },
    "duration": "54 min",
    "rating": "G - All Ages",
    "score": 6.5,
    "scored_by": 143,
    "rank": 7052,
    "popularity": 15272,
    "members": 723,
    "favorites": 0,
    "synopsis": "Chieri is a 6th grade elementary school girl. Her father died when she was little, so she lives with just her mother. The only friend of Chieri had been a stuffed doll Cherry which she found on a storehouse at the time of her father's funeral. In Chieri's world of fantasy, Cherry had talked and played with, and adviced and protected her in place of her father. Chieri visits her grandmother's house for a first time in a while to attend her father's remembrance ceremony. There, she finds a stray dog being about to give birth to puppies. But a crow and strange monster come trying to get the pups. Can Chieri and Cherry save their lives?\n\n(Source: Tokyo International Film Festival)",
    "background": "Chieri to Cherry is an original puppet animation project partially supported by the crowdfunding platform. The project began soliciting donations on May 28, 2015, and achieved its 5 million yen funding target on July 22. It premiered later that year at the 28th Tokyo International Film Festival on October 24.",
    "season": null,
    "year": null,
    "broadcast": {
      "day": null,
      "time": null,
      "timezone": null,
      "string": null
    },
    "producers": [
      {
        "mal_id": 61,
        "type": "anime",
        "name": "Frontier Works",
        "url": "https://myanimelist.net/anime/producer/61/Frontier_Works"
      }
    ],
    "licensors": [],
    "studios": [
      {
        "mal_id": 2596,
        "type": "anime",
        "name": "Comma Studio",
        "url": "https://myanimelist.net/anime/producer/2596/Comma_Studio"
      }
    ],
    "genres": [
      {
        "mal_id": 2,
        "type": "anime",
        "name": "Adventure",
        "url": "https://myanimelist.net/anime/genre/2/Adventure"
      },
      {
        "mal_id": 10,
        "type": "anime",
        "name": "Fantasy",
        "url": "https://myanimelist.net/anime/genre/10/Fantasy"
      }
    ],
    "explicit_genres": [],
    "themes": [],
    "demographics": [],
    "relations": [],
    "theme": {
      "openings": [],
      "endings": [
        "\"Aozora (青空)\" by Salyu"
      ]
    },
    "external": [
      {
        "name": "Official Site",
        "url": "http://www.chieriandcherry.com/"
      },
      {
        "name": "AniDB",
        "url": "https://anidb.net/perl-bin/animedb.pl?show=anime&aid=11371"
      }
    ],
    "streaming": []
  }
}