{
  "data": {
    "mal_id": 31299,
    "url": "https://myanimelist.net/anime/31299/Tao_Hua_Yuan_Ji",
    "images": {
      "jpg": {
        "image_url": "https://cdn.myanimelist.net/images/anime/3/75288.jpg",
        "small_image_url": "https://cdn.myanimelist.net/images/anime/3/75288t.jpg",
        "large_image_url": "https://cdn.myanimelist.net/images/anime/3/75288l.jpg"
      },
      "webp": {
        "image_url": "https://cdn.myanimelist.net/images/anime/3/75288.webp",
        "small_image_url": "https://cdn.myanimelist.net/images/anime/3/75288t.webp",
        "large_image_url": "https://cdn.myanimelist.net/images/anime/3/75288l.webp"
      }
    },
    "trailer": {
      "youtube_id": null,
      "url": null,
      "embed_url": null,
      "images": {
        "image_url": null,
        "small_image_url": null,
        "medium_image_url": null,
        "large_image_url": null,
        "maximum_image_url": null
      }
    },
    "approved": true,
    "titles": [
      {
        "type": "Default",
        "title": "Tao Hua Yuan Ji"
      },
      {
        "type": "Japanese",
        "title": "桃花源记"
      },
      {
        "type": "English",
        "title": "The Legend of Shangri-La"
      }
    ],
    "title": "Tao Hua Yuan Ji",
    "title_english": "The Legend of Shangri-La",
    "title_japanese": "桃花源记",
    "title_synonyms": [],
    "type": "Movie",
    "source": "Other",
    "episodes": 1,
    "status": "Finished Airing",
    "airing": false,
    "aired": {
      "from": "2006-01-01T00:00:00+00:00",
      "to": null,
      "prop": {
        "from": {
          "day": 1,
          "month": 1,
          "year": 2006
        },
        "to": {
          "day": null,
          "month": null,
          "year": null
        }
      },
      "string": "2006"
    },
    "duration": "14 min",
    "rating": "G - All Ages",
    "score": 5.91,
    "scored_by": 173,
    "rank": 10392,
    "popularity": 16895,
    "members": 500,
    "favorites": 0,
    "synopsis": "The 3D CG short film with its unique visual style, which tranquilly depicts Peach Blossom Valley (known to the western culture as Shangri-La), the earthly paradise, in Dong Jin people's mind and their desire to return to happy and harmonic life.\n\n(Source: Official site)",
    "background": "CG Animation Short Film \"The Legend of Shangri-La\" is adapted from the poem of the same title by the famous poet Tao Yuan Ming of Dong Jin Dynasty over 1000 years ago. By applying Chinese traditional painting techniques and papercutting to CG, IDMT created this unique animation film with the style and movement of Shan-Xi shadow puppet show. This short film has won numerous national and international awards. (Source: Official site)",
    "season": null,
    "year": null,
    "broadcast": {
      "day": null,
      "time": null,
      "timezone": null,
      "string": null
    },
    "producers": [],
    "licensors": [],
    "studios": [],
    "genres": [
      {
        "mal_id": 10,
        "type": "anime",
        "name": "Fantasy",
        "url": "https://myanimelist.net/anime/genre/10/Fantasy"
      }
    ],
    "explicit_genres": [],
    "themes": [
      {
        "mal_id": 13,
        "type": "anime",
        "name": "Historical",
        "url": "https://myanimelist.net/anime/genre/13/Historical"
      }
    ],
    "demographics": [],
    "relations": [],
    "theme": {
      "openings": [],
      "endings": []
    },
    "external": [
      {
        "name": "Official Site",
        "url": "http://sz.gdc-world.com/szidmt/case/case_3d_thy.htm"
      },
      {
        "name": "AniDB",
        "url": "https://anidb.net/perl-bin/animedb.pl?show=anime&aid=11411"
      }
    ],
    "streaming": []
  }
}