{
  "data": {
    "mal_id": 34777,
    "url": "https://myanimelist.net/anime/34777/91_Days__Toki_no_Asase_Subete_no_Kinou_Ashita_Mata_Ashita",
    "images": {
      "jpg": {
        "image_url": "https://cdn.myanimelist.net/images/anime/1692/132999.jpg",
        "small_image_url": "https://cdn.myanimelist.net/images/anime/1692/132999t.jpg",
        "large_image_url": "https://cdn.myanimelist.net/images/anime/1692/132999l.jpg"
      },
      "webp": {
        "image_url": "https://cdn.myanimelist.net/images/anime/1692/132999.webp",
        "small_image_url": "https://cdn.myanimelist.net/images/anime/1692/132999t.webp",
        "large_image_url": "https://cdn.myanimelist.net/images/anime/1692/132999l.webp"
      }
    },
    "trailer": {
      "youtube_id": "uq2R9HBpKLI",
      "url": "https://www.youtube.com/watch?v=uq2R9HBpKLI",
      "embed_url": "https://www.youtube.com/embed/uq2R9HBpKLI?enablejsapi=1&wmode=opaque&autoplay=1",
      "images": {
        "image_url": "https://img.youtube.com/vi/uq2R9HBpKLI/default.jpg",
        "small_image_url": "https://img.youtube.com/vi/uq2R9HBpKLI/sddefault.jpg",
        "medium_image_url": "https://img.youtube.com/vi/uq2R9HBpKLI/mqdefault.jpg",
        "large_image_url": "https://img.youtube.com/vi/uq2R9HBpKLI/hqdefault.jpg",
        "maximum_image_url": "https://img.youtube.com/vi/uq2R9HBpKLI/maxresdefault.jpg"
      }
    },
    "approved": true,
    "titles": [
      {
        "type": "Default",
        "title": "91 Days: Toki no Asase/Subete no Kinou/Ashita, Mata Ashita"
      },
      {
        "type": "Synonym",
        "title": "91 Days Episode 13"
      },
      {
        "type": "Synonym",
        "title": "91 Days Special"
      },
      {
        "type": "Japanese",
        "title": "91Days Day13「時の浅瀬／すべての昨日／明日、また明日」"
      },
      {
        "type": "English",
        "title": "91 Days: Shoal of Time/All Our Yesterdays/Tomorrow and Tomorrow"
      },
      {
        "type": "German",
        "title": "91 Days: Folge 13 Untiefen der Zeit/Alle gestrigen Tage/ Morgen und wieder Morgen"
      },
      {
        "type": "Spanish",
        "title": "91 Days Episodio 13 – El Bajío del Tiempo / Todo nuestro Ayer / Mañana y mañana"
      },
      {
        "type": "French",
        "title": "91 Days Episode 13"
      }
    ],
    "title": "91 Days: Toki no Asase/Subete no Kinou/Ashita, Mata Ashita",
    "title_english": "91 Days: Shoal of Time/All Our Yesterdays/Tomorrow and Tomorrow",
    "title_japanese": "91Days Day13「時の浅瀬／すべての昨日／明日、また明日」",
    "title_synonyms": [
      "91 Days Episode 13",
      "91 Days Special"
    ],
    "type": "Special",
    "source": "Original",
    "episodes": 1,
    "status": "Finished Airing",
    "airing": false,
    "aired": {
      "from": "2017-07-05T00:00:00+00:00",
      "to": null,
      "prop": {
        "from": {
          "day": 5,
          "month": 7,
          "year": 2017
        },
        "to": {
          "day": null,
          "month": null,
          "year": null
        }
      },
      "string": "Jul 5, 2017"
    },
    "duration": "24 min",
    "rating": "R - 17+ (violence & profanity)",
    "score": 6.9,
    "scored_by": 30672,
    "rank": 4798,
    "popularity": 3042,
    "members": 58081,
    "favorites": 33,
    "synopsis": "1. Toki no Asase (Shoal of Time)\n2. Subete no Kinou (All Our Yesterdays)\n3. Ashita, Mata Ashita (Tomorrow and Tomorrow)",
    "background": "91 Days: Toki no Asase/Subete no Kinou/Ashita, Mata Ashita was included with the Blu-ray and DVD bundle of 91 Days, released by Funimation Entertainment on November 14, 2017.",
    "season": null,
    "year": null,
    "broadcast": {
      "day": null,
      "time": null,
      "timezone": null,
      "string": null
    },
    "producers": [],
    "licensors": [
      {
        "mal_id": 102,
        "type": "anime",
        "name": "Funimation",
        "url": "https://myanimelist.net/anime/producer/102/Funimation"
      }
    ],
    "studios": [
      {
        "mal_id": 1119,
        "type": "anime",
        "name": "Shuka",
        "url": "https://myanimelist.net/anime/producer/1119/Shuka"
      }
    ],
    "genres": [
      {
        "mal_id": 1,
        "type": "anime",
        "name": "Action",
        "url": "https://myanimelist.net/anime/genre/1/Action"
      },
      {
        "mal_id": 8,
        "type": "anime",
        "name": "Drama",
        "url": "https://myanimelist.net/anime/genre/8/Drama"
      },
      {
        "mal_id": 41,
        "type": "anime",
        "name": "Suspense",
        "url": "https://myanimelist.net/anime/genre/41/Suspense"
      }
    ],
    "explicit_genres": [],
    "themes": [
      {
        "mal_id": 50,
        "type": "anime",
        "name": "Adult Cast",
        "url": "https://myanimelist.net/anime/genre/50/Adult_Cast"
      },
      {
        "mal_id": 13,
        "type": "anime",
        "name": "Historical",
        "url": "https://myanimelist.net/anime/genre/13/Historical"
      },
      {
        "mal_id": 68,
        "type": "anime",
        "name": "Organized Crime",
        "url": "https://myanimelist.net/anime/genre/68/Organized_Crime"
      }
    ],
    "demographics": [],
    "relations": [
      {
        "relation": "Prequel",
        "entry": [
          {
            "mal_id": 32998,
            "type": "anime",
            "name": "91 Days",
            "url": "https://myanimelist.net/anime/32998/91_Days"
          }
        ]
      }
    ],
    "theme": {
      "openings": [
        "\"Signal\" by TK from Ling Tosite Sigure"
      ],
      "endings": [
        "\"Rain or Shine\" by ELISA"
      ]
    },
    "external": [
      {
        "name": "Official Site",
        "url": "http://www.91days.family/bluraydvd/"
      }
    ],
    "streaming": [
      {
        "name": "Crunchyroll",
        "url": "http://www.crunchyroll.com/series-270679"
      }
    ]
  }
}