{
  "data": {
    "mal_id": 36272,
    "url": "https://myanimelist.net/anime/36272/Manichi_ga_Tsurai_Kimochi_Wakarimasu_ka__Yurusenai_Net_Ijime",
    "images": {
      "jpg": {
        "image_url": "https://cdn.myanimelist.net/images/anime/7/87610.jpg",
        "small_image_url": "https://cdn.myanimelist.net/images/anime/7/87610t.jpg",
        "large_image_url": "https://cdn.myanimelist.net/images/anime/7/87610l.jpg"
      },
      "webp": {
        "image_url": "https://cdn.myanimelist.net/images/anime/7/87610.webp",
        "small_image_url": "https://cdn.myanimelist.net/images/anime/7/87610t.webp",
        "large_image_url": "https://cdn.myanimelist.net/images/anime/7/87610l.webp"
      }
    },
    "trailer": {
      "youtube_id": null,
      "url": null,
      "embed_url": null,
      "images": {
        "image_url": null,
        "small_image_url": null,
        "medium_image_url": null,
        "large_image_url": null,
        "maximum_image_url": null
      }
    },
    "approved": true,
    "titles": [
      {
        "type": "Default",
        "title": "Manichi ga Tsurai Kimochi Wakarimasu ka: Yurusenai! Net Ijime"
      },
      {
        "type": "Japanese",
        "title": "毎日がつらい気持ちわかりますか ゆるせない！ネットいじめ"
      }
    ],
    "title": "Manichi ga Tsurai Kimochi Wakarimasu ka: Yurusenai! Net Ijime",
    "title_english": null,
    "title_japanese": "毎日がつらい気持ちわかりますか ゆるせない！ネットいじめ",
    "title_synonyms": [],
    "type": "OVA",
    "source": "Original",
    "episodes": 1,
    "status": "Finished Airing",
    "airing": false,
    "aired": {
      "from": "2014-01-01T00:00:00+00:00",
      "to": null,
      "prop": {
        "from": {
          "day": 1,
          "month": 1,
          "year": 2014
        },
        "to": {
          "day": null,
          "month": null,
          "year": null
        }
      },
      "string": "2014"
    },
    "duration": "18 min",
    "rating": "G - All Ages",
    "score": null,
    "scored_by": null,
    "rank": 17336,
    "popularity": 22147,
    "members": 160,
    "favorites": 0,
    "synopsis": "An educational film about cyberbullying among children. How the words said online or in mobile messages can affect a child which can lead to self harm and suicide.",
    "background": "",
    "season": null,
    "year": null,
    "broadcast": {
      "day": null,
      "time": null,
      "timezone": null,
      "string": null
    },
    "producers": [],
    "licensors": [],
    "studios": [],
    "genres": [],
    "explicit_genres": [],
    "themes": [],
    "demographics": [
      {
        "mal_id": 15,
        "type": "anime",
        "name": "Kids",
        "url": "https://myanimelist.net/anime/genre/15/Kids"
      }
    ],
    "relations": [],
    "theme": {
      "openings": [],
      "endings": []
    },
    "external": [
      {
        "name": "Official Site",
        "url": "http://www.optical.jp/dvd/bohan_detail.html"
      }
    ],
    "streaming": []
  }
}