{
  "data": {
    "mal_id": 39654,
    "url": "https://myanimelist.net/anime/39654/Cinderella_Girls_Gekijou__Kayou_Cinderella_Theater_4th_Season",
    "images": {
      "jpg": {
        "image_url": "https://cdn.myanimelist.net/images/anime/1277/100399.jpg",
        "small_image_url": "https://cdn.myanimelist.net/images/anime/1277/100399t.jpg",
        "large_image_url": "https://cdn.myanimelist.net/images/anime/1277/100399l.jpg"
      },
      "webp": {
        "image_url": "https://cdn.myanimelist.net/images/anime/1277/100399.webp",
        "small_image_url": "https://cdn.myanimelist.net/images/anime/1277/100399t.webp",
        "large_image_url": "https://cdn.myanimelist.net/images/anime/1277/100399l.webp"
      }
    },
    "trailer": {
      "youtube_id": null,
      "url": null,
      "embed_url": null,
      "images": {
        "image_url": null,
        "small_image_url": null,
        "medium_image_url": null,
        "large_image_url": null,
        "maximum_image_url": null
      }
    },
    "approved": true,
    "titles": [
      {
        "type": "Default",
        "title": "Cinderella Girls Gekijou: Kayou Cinderella Theater 4th Season"
      },
      {
        "type": "Synonym",
        "title": "THE IDOLM@STER CINDERELLA GIRLS Theater: Tuesday Cinderella Theater 4th Season"
      },
      {
        "type": "Synonym",
        "title": "Idolmaster Cinderella Girls Theater: Tuesday Cinderella Theater 4th Season"
      },
      {
        "type": "Synonym",
        "title": "Cingeki (Web) 4th Season"
      },
      {
        "type": "Japanese",
        "title": "シンデレラガールズ劇場 火曜シンデレラシアター 第4期"
      },
      {
        "type": "English",
        "title": "THE IDOLM@STER CINDERELLA GIRLS Theater (Web) 4th Season"
      }
    ],
    "title": "Cinderella Girls Gekijou: Kayou Cinderella Theater 4th Season",
    "title_english": "THE IDOLM@STER CINDERELLA GIRLS Theater (Web) 4th Season",
    "title_japanese": "シンデレラガールズ劇場 火曜シンデレラシアター 第4期",
    "title_synonyms": [
      "THE IDOLM@STER CINDERELLA GIRLS Theater: Tuesday Cinderella Theater 4th Season",
      "Idolmaster Cinderella Girls Theater: Tuesday Cinderella Theater 4th Season",
      "Cingeki (Web) 4th Season"
    ],
    "type": "ONA",
    "source": "4-koma manga",
    "episodes": 7,
    "status": "Finished Airing",
    "airing": false,
    "aired": {
      "from": "2019-04-02T00:00:00+00:00",
      "to": "2019-06-25T00:00:00+00:00",
      "prop": {
        "from": {
          "day": 2,
          "month": 4,
          "year": 2019
        },
        "to": {
          "day": 25,
          "month": 6,
          "year": 2019
        }
      },
      "string": "Apr 2, 2019 to Jun 25, 2019"
    },
    "duration": "1 min per ep",
    "rating": "PG-13 - Teens 13 or older",
    "score": 6.29,
    "scored_by": 1132,
    "rank": 8321,
    "popularity": 10481,
    "members": 2992,
    "favorites": 0,
    "synopsis": "Bonus segments of Cinderella Girls Gekijou 4th Season streamed on The iDOLM@STER Cinderella Girls Mobage following the television broadcast.",
    "background": "",
    "season": null,
    "year": null,
    "broadcast": {
      "day": null,
      "time": null,
      "timezone": null,
      "string": null
    },
    "producers": [],
    "licensors": [],
    "studios": [
      {
        "mal_id": 400,
        "type": "anime",
        "name": "Gathering",
        "url": "https://myanimelist.net/anime/producer/400/Gathering"
      },
      {
        "mal_id": 1829,
        "type": "anime",
        "name": "Lesprit",
        "url": "https://myanimelist.net/anime/producer/1829/Lesprit"
      }
    ],
    "genres": [
      {
        "mal_id": 4,
        "type": "anime",
        "name": "Comedy",
        "url": "https://myanimelist.net/anime/genre/4/Comedy"
      },
      {
        "mal_id": 36,
        "type": "anime",
        "name": "Slice of Life",
        "url": "https://myanimelist.net/anime/genre/36/Slice_of_Life"
      }
    ],
    "explicit_genres": [],
    "themes": [],
    "demographics": [],
    "relations": [
      {
        "relation": "Prequel",
        "entry": [
          {
            "mal_id": 37424,
            "type": "anime",
            "name": "Cinderella Girls Gekijou: Kayou Cinderella Theater 3rd Season",
            "url": "https://myanimelist.net/anime/37424/Cinderella_Girls_Gekijou__Kayou_Cinderella_Theater_3rd_Season"
          }
        ]
      },
      {
        "relation": "Parent Story",
        "entry": [
          {
            "mal_id": 38767,
            "type": "anime",
            "name": "Cinderella Girls Gekijou: Climax Season",
            "url": "https://myanimelist.net/anime/38767/Cinderella_Girls_Gekijou__Climax_Season"
          }
        ]
      }
    ],
    "theme": {
      "openings": [],
      "endings": []
    },
    "external": [
      {
        "name": "Official Site",
        "url": "http://www.cingeki-anime.com/"
      },
      {
        "name": "AniDB",
        "url": "https://anidb.net/perl-bin/animedb.pl?show=anime&aid=14516"
      },
      {
        "name": "ANN",
        "url": "https://www.animenewsnetwork.com/encyclopedia/anime.php?id=21987"
      },
      {
        "name": "Wikipedia",
        "url": "https://ja.wikipedia.org/wiki/%E3%82%B7%E3%83%B3%E3%83%87%E3%83%AC%E3%83%A9%E3%82%AC%E3%83%BC%E3%83%AB%E3%82%BA%E5%8A%87%E5%A0%B4"
      }
    ],
    "streaming": []
  }
}