{
  "data": {
    "mal_id": 5210,
    "url": "https://myanimelist.net/anime/5210/Houkago_2_The_Animation",
    "images": {
      "jpg": {
        "image_url": "https://cdn.myanimelist.net/images/anime/1959/104006.jpg",
        "small_image_url": "https://cdn.myanimelist.net/images/anime/1959/104006t.jpg",
        "large_image_url": "https://cdn.myanimelist.net/images/anime/1959/104006l.jpg"
      },
      "webp": {
        "image_url": "https://cdn.myanimelist.net/images/anime/1959/104006.webp",
        "small_image_url": "https://cdn.myanimelist.net/images/anime/1959/104006t.webp",
        "large_image_url": "https://cdn.myanimelist.net/images/anime/1959/104006l.webp"
      }
    },
    "trailer": {
      "youtube_id": null,
      "url": null,
      "embed_url": null,
      "images": {
        "image_url": null,
        "small_image_url": null,
        "medium_image_url": null,
        "large_image_url": null,
        "maximum_image_url": null
      }
    },
    "approved": true,
    "titles": [
      {
        "type": "Default",
        "title": "Houkago 2 The Animation"
      },
      {
        "type": "Japanese",
        "title": "放課後2 THE ANIMATION"
      }
    ],
    "title": "Houkago 2 The Animation",
    "title_english": null,
    "title_japanese": "放課後2 THE ANIMATION",
    "title_synonyms": [],
    "type": "OVA",
    "source": "Visual novel",
    "episodes": 1,
    "status": "Finished Airing",
    "airing": false,
    "aired": {
      "from": "2007-08-31T00:00:00+00:00",
      "to": null,
      "prop": {
        "from": {
          "day": 31,
          "month": 8,
          "year": 2007
        },
        "to": {
          "day": null,
          "month": null,
          "year": null
        }
      },
      "string": "Aug 31, 2007"
    },
    "duration": "30 min",
    "rating": "Rx - Hentai",
    "score": 5.76,
    "scored_by": 1318,
    "rank": null,
    "popularity": 9359,
    "members": 4248,
    "favorites": 9,
    "synopsis": "Ryuichi's first sex doesn't go well and he can't get an erection since then. He starts to work at a girl's high school as a janitor but his work attitudes are terrible, so his dismissal is decided. When he is depressed to hear that, he meets Midori. And he gets an erection while talking to her. He can't stand it and rapes her. He has only one month to go so he decides to spend his time at school raping as many girls as possible....\n\n(Source: ErogeShop)",
    "background": "",
    "season": null,
    "year": null,
    "broadcast": {
      "day": null,
      "time": null,
      "timezone": null,
      "string": null
    },
    "producers": [
      {
        "mal_id": 138,
        "type": "anime",
        "name": "Himajin Planning",
        "url": "https://myanimelist.net/anime/producer/138/Himajin_Planning"
      }
    ],
    "licensors": [],
    "studios": [
      {
        "mal_id": 405,
        "type": "anime",
        "name": "T-Rex",
        "url": "https://myanimelist.net/anime/producer/405/T-Rex"
      }
    ],
    "genres": [
      {
        "mal_id": 12,
        "type": "anime",
        "name": "Hentai",
        "url": "https://myanimelist.net/anime/genre/12/Hentai"
      }
    ],
    "explicit_genres": [],
    "themes": [],
    "demographics": [],
    "relations": [
      {
        "relation": "Sequel",
        "entry": [
          {
            "mal_id": 5213,
            "type": "anime",
            "name": "Houkago 2: Sayuri",
            "url": "https://myanimelist.net/anime/5213/Houkago_2__Sayuri"
          }
        ]
      },
      {
        "relation": "Adaptation",
        "entry": [
          {
            "mal_id": 97904,
            "type": "manga",
            "name": "Houkago 2: Hakudaku no Lesson",
            "url": "https://myanimelist.net/manga/97904/Houkago_2__Hakudaku_no_Lesson"
          }
        ]
      },
      {
        "relation": "Other",
        "entry": [
          {
            "mal_id": 2896,
            "type": "anime",
            "name": "Houkago: Nureta Seifuku",
            "url": "https://myanimelist.net/anime/2896/Houkago__Nureta_Seifuku"
          }
        ]
      }
    ],
    "theme": {
      "openings": [],
      "endings": []
    },
    "external": [
      {
        "name": "AniDB",
        "url": "https://anidb.net/perl-bin/animedb.pl?show=anime&aid=5365"
      },
      {
        "name": "ANN",
        "url": "https://www.animenewsnetwork.com/encyclopedia/anime.php?id=8504"
      }
    ],
    "streaming": []
  }
}