{
  "data": {
    "mal_id": 52706,
    "url": "https://myanimelist.net/anime/52706/Dongwu_Kuanghuan_Jie",
    "images": {
      "jpg": {
        "image_url": "https://cdn.myanimelist.net/images/anime/1004/126801.jpg",
        "small_image_url": "https://cdn.myanimelist.net/images/anime/1004/126801t.jpg",
        "large_image_url": "https://cdn.myanimelist.net/images/anime/1004/126801l.jpg"
      },
      "webp": {
        "image_url": "https://cdn.myanimelist.net/images/anime/1004/126801.webp",
        "small_image_url": "https://cdn.myanimelist.net/images/anime/1004/126801t.webp",
        "large_image_url": "https://cdn.myanimelist.net/images/anime/1004/126801l.webp"
      }
    },
    "trailer": {
      "youtube_id": null,
      "url": null,
      "embed_url": null,
      "images": {
        "image_url": null,
        "small_image_url": null,
        "medium_image_url": null,
        "large_image_url": null,
        "maximum_image_url": null
      }
    },
    "approved": true,
    "titles": [
      {
        "type": "Default",
        "title": "Dongwu Kuanghuan Jie"
      },
      {
        "type": "Japanese",
        "title": "动物狂欢节"
      },
      {
        "type": "English",
        "title": "Carnival of The Animals"
      }
    ],
    "title": "Dongwu Kuanghuan Jie",
    "title_english": "Carnival of The Animals",
    "title_japanese": "动物狂欢节",
    "title_synonyms": [],
    "type": "Movie",
    "source": "Original",
    "episodes": 1,
    "status": "Finished Airing",
    "airing": false,
    "aired": {
      "from": "2009-01-28T00:00:00+00:00",
      "to": null,
      "prop": {
        "from": {
          "day": 28,
          "month": 1,
          "year": 2009
        },
        "to": {
          "day": null,
          "month": null,
          "year": null
        }
      },
      "string": "Jan 28, 2009"
    },
    "duration": "1 hr 12 min",
    "rating": "PG - Children",
    "score": null,
    "scored_by": null,
    "rank": 20188,
    "popularity": 23861,
    "members": 108,
    "favorites": 0,
    "synopsis": null,
    "background": "Runner-up of Best Animation Feature at the 26th Golden Rooster Awards.",
    "season": null,
    "year": null,
    "broadcast": {
      "day": null,
      "time": null,
      "timezone": null,
      "string": null
    },
    "producers": [],
    "licensors": [],
    "studios": [],
    "genres": [
      {
        "mal_id": 4,
        "type": "anime",
        "name": "Comedy",
        "url": "https://myanimelist.net/anime/genre/4/Comedy"
      },
      {
        "mal_id": 10,
        "type": "anime",
        "name": "Fantasy",
        "url": "https://myanimelist.net/anime/genre/10/Fantasy"
      }
    ],
    "explicit_genres": [],
    "themes": [
      {
        "mal_id": 51,
        "type": "anime",
        "name": "Anthropomorphic",
        "url": "https://myanimelist.net/anime/genre/51/Anthropomorphic"
      }
    ],
    "demographics": [],
    "relations": [],
    "theme": {
      "openings": [],
      "endings": []
    },
    "external": [],
    "streaming": []
  }
}