{
  "data": {
    "mal_id": 52836,
    "url": "https://myanimelist.net/anime/52836/Baixian",
    "images": {
      "jpg": {
        "image_url": "https://cdn.myanimelist.net/images/anime/1640/127211.jpg",
        "small_image_url": "https://cdn.myanimelist.net/images/anime/1640/127211t.jpg",
        "large_image_url": "https://cdn.myanimelist.net/images/anime/1640/127211l.jpg"
      },
      "webp": {
        "image_url": "https://cdn.myanimelist.net/images/anime/1640/127211.webp",
        "small_image_url": "https://cdn.myanimelist.net/images/anime/1640/127211t.webp",
        "large_image_url": "https://cdn.myanimelist.net/images/anime/1640/127211l.webp"
      }
    },
    "trailer": {
      "youtube_id": null,
      "url": null,
      "embed_url": null,
      "images": {
        "image_url": null,
        "small_image_url": null,
        "medium_image_url": null,
        "large_image_url": null,
        "maximum_image_url": null
      }
    },
    "approved": true,
    "titles": [
      {
        "type": "Default",
        "title": "Baixian"
      },
      {
        "type": "Japanese",
        "title": "白線"
      },
      {
        "type": "English",
        "title": "Realign"
      }
    ],
    "title": "Baixian",
    "title_english": "Realign",
    "title_japanese": "白線",
    "title_synonyms": [],
    "type": "Movie",
    "source": "Original",
    "episodes": 1,
    "status": "Finished Airing",
    "airing": false,
    "aired": {
      "from": "2022-06-23T00:00:00+00:00",
      "to": null,
      "prop": {
        "from": {
          "day": 23,
          "month": 6,
          "year": 2022
        },
        "to": {
          "day": null,
          "month": null,
          "year": null
        }
      },
      "string": "Jun 23, 2022"
    },
    "duration": "16 min",
    "rating": "PG-13 - Teens 13 or older",
    "score": null,
    "scored_by": null,
    "rank": 19262,
    "popularity": 18768,
    "members": 348,
    "favorites": 1,
    "synopsis": "Baixian is an animation film about space and time dimension. It depicts a boy who decides to walk towards the line that behold the gravity after thunderstorms corroded time.\n\n(Source: Taipei Film Festival)",
    "background": "",
    "season": null,
    "year": null,
    "broadcast": {
      "day": null,
      "time": null,
      "timezone": null,
      "string": null
    },
    "producers": [],
    "licensors": [],
    "studios": [],
    "genres": [
      {
        "mal_id": 8,
        "type": "anime",
        "name": "Drama",
        "url": "https://myanimelist.net/anime/genre/8/Drama"
      },
      {
        "mal_id": 10,
        "type": "anime",
        "name": "Fantasy",
        "url": "https://myanimelist.net/anime/genre/10/Fantasy"
      }
    ],
    "explicit_genres": [],
    "themes": [],
    "demographics": [],
    "relations": [],
    "theme": {
      "openings": [],
      "endings": []
    },
    "external": [],
    "streaming": []
  }
}