{
  "data": {
    "mal_id": 53698,
    "url": "https://myanimelist.net/anime/53698/World_Dai_Star",
    "images": {
      "jpg": {
        "image_url": "https://cdn.myanimelist.net/images/anime/1203/133808.jpg",
        "small_image_url": "https://cdn.myanimelist.net/images/anime/1203/133808t.jpg",
        "large_image_url": "https://cdn.myanimelist.net/images/anime/1203/133808l.jpg"
      },
      "webp": {
        "image_url": "https://cdn.myanimelist.net/images/anime/1203/133808.webp",
        "small_image_url": "https://cdn.myanimelist.net/images/anime/1203/133808t.webp",
        "large_image_url": "https://cdn.myanimelist.net/images/anime/1203/133808l.webp"
      }
    },
    "trailer": {
      "youtube_id": "VXArZL0xF40",
      "url": "https://www.youtube.com/watch?v=VXArZL0xF40",
      "embed_url": "https://www.youtube.com/embed/VXArZL0xF40?enablejsapi=1&wmode=opaque&autoplay=1",
      "images": {
        "image_url": "https://img.youtube.com/vi/VXArZL0xF40/default.jpg",
        "small_image_url": "https://img.youtube.com/vi/VXArZL0xF40/sddefault.jpg",
        "medium_image_url": "https://img.youtube.com/vi/VXArZL0xF40/mqdefault.jpg",
        "large_image_url": "https://img.youtube.com/vi/VXArZL0xF40/hqdefault.jpg",
        "maximum_image_url": "https://img.youtube.com/vi/VXArZL0xF40/maxresdefault.jpg"
      }
    },
    "approved": true,
    "titles": [
      {
        "type": "Default",
        "title": "World Dai Star"
      },
      {
        "type": "Japanese",
        "title": "ワールドダイスター"
      },
      {
        "type": "English",
        "title": "Stella of the Theater: World Dai Star"
      }
    ],
    "title": "World Dai Star",
    "title_english": "Stella of the Theater: World Dai Star",
    "title_japanese": "ワールドダイスター",
    "title_synonyms": [],
    "type": "TV",
    "source": "Mixed media",
    "episodes": 12,
    "status": "Finished Airing",
    "airing": false,
    "aired": {
      "from": "2023-04-09T00:00:00+00:00",
      "to": "2023-06-25T00:00:00+00:00",
      "prop": {
        "from": {
          "day": 9,
          "month": 4,
          "year": 2023
        },
        "to": {
          "day": 25,
          "month": 6,
          "year": 2023
        }
      },
      "string": "Apr 9, 2023 to Jun 25, 2023"
    },
    "duration": "24 min per ep",
    "rating": "PG-13 - Teens 13 or older",
    "score": 7.32,
    "scored_by": 5366,
    "rank": 2749,
    "popularity": 5583,
    "members": 15846,
    "favorites": 87,
    "synopsis": "In the 20th century, the world is experiencing a musical theater boom. Top performers known as Dai Stars enthrall the audience with their marvelous acting and singing. Among them, the greatest performers are given the title World Dai Star.\n\nYoung and inexperienced Kokona Ootori dreams of being recognized as a World Dai Star. After multiple failures, she finally gets another chance to audition for the world-renowned theater troupe Sirius. Inspired by her best friend Shizuka, Kokona takes the first steps toward her goal and works hard to improve her acting. However, the world of theater is fiercely competitive, as many other girls seek the spotlight—including Kathrina Griebel, a talented performer from Germany. In order to fulfill her dream, Kokona needs to earn the right to stand on stage above all else.\n\n[Written by MAL Rewrite]",
    "background": "",
    "season": "spring",
    "year": 2023,
    "broadcast": {
      "day": "Sundays",
      "time": "23:00",
      "timezone": "Asia/Tokyo",
      "string": "Sundays at 23:00 (JST)"
    },
    "producers": [
      {
        "mal_id": 101,
        "type": "anime",
        "name": "Studio Hibari",
        "url": "https://myanimelist.net/anime/producer/101/Studio_Hibari"
      },
      {
        "mal_id": 104,
        "type": "anime",
        "name": "Lantis",
        "url": "https://myanimelist.net/anime/producer/104/Lantis"
      },
      {
        "mal_id": 1261,
        "type": "anime",
        "name": "Good Smile Company",
        "url": "https://myanimelist.net/anime/producer/1261/Good_Smile_Company"
      },
      {
        "mal_id": 1444,
        "type": "anime",
        "name": "Egg Firm",
        "url": "https://myanimelist.net/anime/producer/1444/Egg_Firm"
      },
      {
        "mal_id": 1946,
        "type": "anime",
        "name": "Hawkeye",
        "url": "https://myanimelist.net/anime/producer/1946/Hawkeye"
      },
      {
        "mal_id": 2289,
        "type": "anime",
        "name": "GREE Entertainment",
        "url": "https://myanimelist.net/anime/producer/2289/GREE_Entertainment"
      },
      {
        "mal_id": 2424,
        "type": "anime",
        "name": "Bandai Namco Filmworks",
        "url": "https://myanimelist.net/anime/producer/2424/Bandai_Namco_Filmworks"
      },
      {
        "mal_id": 2425,
        "type": "anime",
        "name": "Bandai Namco Music Live",
        "url": "https://myanimelist.net/anime/producer/2425/Bandai_Namco_Music_Live"
      },
      {
        "mal_id": 2741,
        "type": "anime",
        "name": "Daito Giken",
        "url": "https://myanimelist.net/anime/producer/2741/Daito_Giken"
      }
    ],
    "licensors": [],
    "studios": [
      {
        "mal_id": 456,
        "type": "anime",
        "name": "Lerche",
        "url": "https://myanimelist.net/anime/producer/456/Lerche"
      }
    ],
    "genres": [],
    "explicit_genres": [],
    "themes": [
      {
        "mal_id": 70,
        "type": "anime",
        "name": "Performing Arts",
        "url": "https://myanimelist.net/anime/genre/70/Performing_Arts"
      }
    ],
    "demographics": [],
    "relations": [],
    "theme": {
      "openings": [
        "\"Wanna Be Star! (ワナビスタ!)\" by Kokona Ootori (CV: Manaka Iwami), Shizuka (CV: Ikumi Hasegawa), Kathrina (CV: Sally Amaki), Yae Niizuma (CV: Maria Naganawa), Panda Yanagiba (CV: Naomi Oozora), Chisa Sasuga (CV: Riko Sasaki) (eps 2-11)"
      ],
      "endings": [
        "2 \"Two of Us (トゥ・オブ・アス)\" by Kokona Ootori (CV: Manaka Iwami), Shizuka (CV: Ikumi Hasegawa) (eps 2-7, 9-10)",
        "3: \"Na mo Naki Koibito yo (名もなき恋人よ)\" by Panda Yanagiba (CV: Naomi Oozora), Chisa Sasuga (CV: Riko Sasaki) (ep 8)",
        "4: \"Wanna Be Star! (ワナビスタ!)\" (Instrumental) (ep 12)",
        "1: \"Wanna Be Star! (ワナビスタ!)\" by Kokona Ootori (CV: Manaka Iwami), Shizuka (CV: Ikumi Hasegawa), Kathrina (CV: Sally Amaki), Yae Niizuma (CV: Maria Naganawa), Panda Yanagiba (CV: Naomi Oozora), Chisa Sasuga (CV: Riko Sasaki) (eps 1)"
      ]
    },
    "external": [
      {
        "name": "Official Site",
        "url": "https://world-dai-star.com/anime"
      },
      {
        "name": "@world_dai_star",
        "url": "https://twitter.com/world_dai_star"
      },
      {
        "name": "AniDB",
        "url": "https://anidb.net/perl-bin/animedb.pl?show=anime&aid=17739"
      },
      {
        "name": "ANN",
        "url": "https://www.animenewsnetwork.com/encyclopedia/anime.php?id=26654"
      },
      {
        "name": "Wikipedia",
        "url": "https://en.wikipedia.org/wiki/World_Dai_Star"
      },
      {
        "name": "Wikipedia",
        "url": "https://ja.wikipedia.org/wiki/%E3%83%AF%E3%83%BC%E3%83%AB%E3%83%89%E3%83%80%E3%82%A4%E3%82%B9%E3%82%BF%E3%83%BC#%E3%83%86%E3%83%AC%E3%83%93%E3%82%A2%E3%83%8B%E3%83%A1"
      },
      {
        "name": "Syoboi",
        "url": "https://cal.syoboi.jp/tid/6641"
      },
      {
        "name": "Bangumi",
        "url": "https://bangumi.tv/subject/409088"
      },
      {
        "name": "Baidu Baike",
        "url": "https://baike.baidu.com/item/World%20Dai%20Star/62381959?fromModule=lemma-qiyi_sense-lemma"
      },
      {
        "name": "Douban",
        "url": "https://movie.douban.com/subject/36158403/"
      }
    ],
    "streaming": [
      {
        "name": "Crunchyroll",
        "url": "https://www.crunchyroll.com/"
      },
      {
        "name": "Aniplus TV",
        "url": "http://www.aniplustv.com/"
      }
    ]
  }
}