{
  "data": {
    "mal_id": 54793,
    "url": "https://myanimelist.net/anime/54793/Bloody_Escape__Jigoku_no_Tousou_Geki",
    "images": {
      "jpg": {
        "image_url": "https://cdn.myanimelist.net/images/anime/1043/139689.jpg",
        "small_image_url": "https://cdn.myanimelist.net/images/anime/1043/139689t.jpg",
        "large_image_url": "https://cdn.myanimelist.net/images/anime/1043/139689l.jpg"
      },
      "webp": {
        "image_url": "https://cdn.myanimelist.net/images/anime/1043/139689.webp",
        "small_image_url": "https://cdn.myanimelist.net/images/anime/1043/139689t.webp",
        "large_image_url": "https://cdn.myanimelist.net/images/anime/1043/139689l.webp"
      }
    },
    "trailer": {
      "youtube_id": "c9Wc-zPf82M",
      "url": "https://www.youtube.com/watch?v=c9Wc-zPf82M",
      "embed_url": "https://www.youtube.com/embed/c9Wc-zPf82M?enablejsapi=1&wmode=opaque&autoplay=1",
      "images": {
        "image_url": "https://img.youtube.com/vi/c9Wc-zPf82M/default.jpg",
        "small_image_url": "https://img.youtube.com/vi/c9Wc-zPf82M/sddefault.jpg",
        "medium_image_url": "https://img.youtube.com/vi/c9Wc-zPf82M/mqdefault.jpg",
        "large_image_url": "https://img.youtube.com/vi/c9Wc-zPf82M/hqdefault.jpg",
        "maximum_image_url": "https://img.youtube.com/vi/c9Wc-zPf82M/maxresdefault.jpg"
      }
    },
    "approved": true,
    "titles": [
      {
        "type": "Default",
        "title": "Bloody Escape: Jigoku no Tousou Geki"
      },
      {
        "type": "Japanese",
        "title": "BLOODY ESCAPE -地獄の逃走劇-"
      }
    ],
    "title": "Bloody Escape: Jigoku no Tousou Geki",
    "title_english": null,
    "title_japanese": "BLOODY ESCAPE -地獄の逃走劇-",
    "title_synonyms": [],
    "type": "Movie",
    "source": "Original",
    "episodes": 1,
    "status": "Finished Airing",
    "airing": false,
    "aired": {
      "from": "2024-01-05T00:00:00+00:00",
      "to": null,
      "prop": {
        "from": {
          "day": 5,
          "month": 1,
          "year": 2024
        },
        "to": {
          "day": null,
          "month": null,
          "year": null
        }
      },
      "string": "Jan 5, 2024"
    },
    "duration": "1 hr 37 min",
    "rating": "PG-13 - Teens 13 or older",
    "score": null,
    "scored_by": null,
    "rank": 19451,
    "popularity": 11436,
    "members": 2251,
    "favorites": 5,
    "synopsis": "After human experimentation turns Kisaragi into a cyborg, he finds himself pressured by multiple organizations: An undying convent of vampires bent on the conquest of Tokyo, and an immortal order of knights, and a group of Yakuza, sword to avenge the killing of their leader. \n\n\"I might not have any reason to live, but that's no reason to let them kill me.\"\n\nKisaragi will have to use his cyborg-body and his unique \"blood,\" as well as anything else he can to make his big escape!!!\n\n(Source: Official Site, translated)",
    "background": "",
    "season": null,
    "year": null,
    "broadcast": {
      "day": null,
      "time": null,
      "timezone": null,
      "string": null
    },
    "producers": [
      {
        "mal_id": 735,
        "type": "anime",
        "name": "Slow Curve",
        "url": "https://myanimelist.net/anime/producer/735/Slow_Curve"
      }
    ],
    "licensors": [],
    "studios": [
      {
        "mal_id": 1023,
        "type": "anime",
        "name": "Polygon Pictures",
        "url": "https://myanimelist.net/anime/producer/1023/Polygon_Pictures"
      }
    ],
    "genres": [
      {
        "mal_id": 1,
        "type": "anime",
        "name": "Action",
        "url": "https://myanimelist.net/anime/genre/1/Action"
      },
      {
        "mal_id": 8,
        "type": "anime",
        "name": "Drama",
        "url": "https://myanimelist.net/anime/genre/8/Drama"
      },
      {
        "mal_id": 24,
        "type": "anime",
        "name": "Sci-Fi",
        "url": "https://myanimelist.net/anime/genre/24/Sci-Fi"
      },
      {
        "mal_id": 37,
        "type": "anime",
        "name": "Supernatural",
        "url": "https://myanimelist.net/anime/genre/37/Supernatural"
      }
    ],
    "explicit_genres": [],
    "themes": [
      {
        "mal_id": 68,
        "type": "anime",
        "name": "Organized Crime",
        "url": "https://myanimelist.net/anime/genre/68/Organized_Crime"
      },
      {
        "mal_id": 32,
        "type": "anime",
        "name": "Vampire",
        "url": "https://myanimelist.net/anime/genre/32/Vampire"
      }
    ],
    "demographics": [],
    "relations": [
      {
        "relation": "Other",
        "entry": [
          {
            "mal_id": 50862,
            "type": "anime",
            "name": "Estab-Life: Great Escape",
            "url": "https://myanimelist.net/anime/50862/Estab-Life__Great_Escape"
          }
        ]
      }
    ],
    "theme": {
      "openings": [],
      "endings": [
        "\"Tokumei Kibou (匿名奇謀)\" by Atsuki Taketomo"
      ]
    },
    "external": [
      {
        "name": "Official Site",
        "url": "https://bloody-escape.com/"
      },
      {
        "name": "@BLOODY__ESCAPE",
        "url": "https://twitter.com/BLOODY__ESCAPE"
      },
      {
        "name": "AniDB",
        "url": "https://anidb.net/perl-bin/animedb.pl?show=anime&aid=17144"
      },
      {
        "name": "ANN",
        "url": "https://www.animenewsnetwork.com/encyclopedia/anime.php?id=27566"
      }
    ],
    "streaming": []
  }
}