{
  "data": {
    "mal_id": 54922,
    "url": "https://myanimelist.net/anime/54922/Short_Flash_Transformers_Series",
    "images": {
      "jpg": {
        "image_url": "https://cdn.myanimelist.net/images/anime/1448/135074.jpg",
        "small_image_url": "https://cdn.myanimelist.net/images/anime/1448/135074t.jpg",
        "large_image_url": "https://cdn.myanimelist.net/images/anime/1448/135074l.jpg"
      },
      "webp": {
        "image_url": "https://cdn.myanimelist.net/images/anime/1448/135074.webp",
        "small_image_url": "https://cdn.myanimelist.net/images/anime/1448/135074t.webp",
        "large_image_url": "https://cdn.myanimelist.net/images/anime/1448/135074l.webp"
      }
    },
    "trailer": {
      "youtube_id": null,
      "url": null,
      "embed_url": null,
      "images": {
        "image_url": null,
        "small_image_url": null,
        "medium_image_url": null,
        "large_image_url": null,
        "maximum_image_url": null
      }
    },
    "approved": true,
    "titles": [
      {
        "type": "Default",
        "title": "Short Flash Transformers Series"
      },
      {
        "type": "Synonym",
        "title": "Transformers Short Series"
      },
      {
        "type": "English",
        "title": "Short Flash Transformers Series"
      }
    ],
    "title": "Short Flash Transformers Series",
    "title_english": "Short Flash Transformers Series",
    "title_japanese": null,
    "title_synonyms": [
      "Transformers Short Series"
    ],
    "type": "ONA",
    "source": "Other",
    "episodes": 52,
    "status": "Finished Airing",
    "airing": false,
    "aired": {
      "from": "2009-10-17T00:00:00+00:00",
      "to": "2020-09-12T00:00:00+00:00",
      "prop": {
        "from": {
          "day": 17,
          "month": 10,
          "year": 2009
        },
        "to": {
          "day": 12,
          "month": 9,
          "year": 2020
        }
      },
      "string": "Oct 17, 2009 to Sep 12, 2020"
    },
    "duration": "50 sec per ep",
    "rating": "PG-13 - Teens 13 or older",
    "score": null,
    "scored_by": null,
    "rank": 14135,
    "popularity": 23489,
    "members": 115,
    "favorites": 0,
    "synopsis": "Short Flash Transformers Series created by Seo-Ro Oh (오서로, Osro).",
    "background": "",
    "season": null,
    "year": null,
    "broadcast": {
      "day": null,
      "time": null,
      "timezone": null,
      "string": null
    },
    "producers": [],
    "licensors": [],
    "studios": [],
    "genres": [
      {
        "mal_id": 1,
        "type": "anime",
        "name": "Action",
        "url": "https://myanimelist.net/anime/genre/1/Action"
      },
      {
        "mal_id": 24,
        "type": "anime",
        "name": "Sci-Fi",
        "url": "https://myanimelist.net/anime/genre/24/Sci-Fi"
      }
    ],
    "explicit_genres": [],
    "themes": [
      {
        "mal_id": 18,
        "type": "anime",
        "name": "Mecha",
        "url": "https://myanimelist.net/anime/genre/18/Mecha"
      }
    ],
    "demographics": [],
    "relations": [],
    "theme": {
      "openings": [],
      "endings": []
    },
    "external": [
      {
        "name": "YouTube",
        "url": "https://www.youtube.com/watch?v=Ne6f6eeWlqo&list=PL6145727E46FF5FD4"
      }
    ],
    "streaming": []
  }
}