{
  "data": {
    "mal_id": 57150,
    "url": "https://myanimelist.net/anime/57150/Creature_Hunters",
    "images": {
      "jpg": {
        "image_url": "https://cdn.myanimelist.net/images/anime/1274/139625.jpg",
        "small_image_url": "https://cdn.myanimelist.net/images/anime/1274/139625t.jpg",
        "large_image_url": "https://cdn.myanimelist.net/images/anime/1274/139625l.jpg"
      },
      "webp": {
        "image_url": "https://cdn.myanimelist.net/images/anime/1274/139625.webp",
        "small_image_url": "https://cdn.myanimelist.net/images/anime/1274/139625t.webp",
        "large_image_url": "https://cdn.myanimelist.net/images/anime/1274/139625l.webp"
      }
    },
    "trailer": {
      "youtube_id": null,
      "url": null,
      "embed_url": null,
      "images": {
        "image_url": null,
        "small_image_url": null,
        "medium_image_url": null,
        "large_image_url": null,
        "maximum_image_url": null
      }
    },
    "approved": true,
    "titles": [
      {
        "type": "Default",
        "title": "Creature Hunters"
      },
      {
        "type": "Japanese",
        "title": "크리처헌터스"
      }
    ],
    "title": "Creature Hunters",
    "title_english": null,
    "title_japanese": "크리처헌터스",
    "title_synonyms": [],
    "type": "TV",
    "source": "Original",
    "episodes": 26,
    "status": "Not yet aired",
    "airing": false,
    "aired": {
      "from": null,
      "to": null,
      "prop": {
        "from": {
          "day": null,
          "month": null,
          "year": null
        },
        "to": {
          "day": null,
          "month": null,
          "year": null
        }
      },
      "string": "Not available"
    },
    "duration": "15 min per ep",
    "rating": "PG - Children",
    "score": null,
    "scored_by": null,
    "rank": null,
    "popularity": 16274,
    "members": 568,
    "favorites": 2,
    "synopsis": null,
    "background": "",
    "season": null,
    "year": null,
    "broadcast": {
      "day": null,
      "time": null,
      "timezone": null,
      "string": "Unknown"
    },
    "producers": [],
    "licensors": [],
    "studios": [],
    "genres": [
      {
        "mal_id": 1,
        "type": "anime",
        "name": "Action",
        "url": "https://myanimelist.net/anime/genre/1/Action"
      },
      {
        "mal_id": 2,
        "type": "anime",
        "name": "Adventure",
        "url": "https://myanimelist.net/anime/genre/2/Adventure"
      }
    ],
    "explicit_genres": [],
    "themes": [
      {
        "mal_id": 18,
        "type": "anime",
        "name": "Mecha",
        "url": "https://myanimelist.net/anime/genre/18/Mecha"
      }
    ],
    "demographics": [
      {
        "mal_id": 15,
        "type": "anime",
        "name": "Kids",
        "url": "https://myanimelist.net/anime/genre/15/Kids"
      }
    ],
    "relations": [],
    "theme": {
      "openings": [],
      "endings": []
    },
    "external": [
      {
        "name": "Official Site",
        "url": "http://www.creaturehunters.net/index.html"
      },
      {
        "name": "Namuwiki",
        "url": "https://namu.wiki/w/크리처헌터스"
      }
    ],
    "streaming": []
  }
}