{
  "data": {
    "mal_id": 9009,
    "url": "https://myanimelist.net/anime/9009/Otome_Juurin_Yuugi__Maiden_Infringement_Play",
    "images": {
      "jpg": {
        "image_url": "https://cdn.myanimelist.net/images/anime/1430/113075.jpg",
        "small_image_url": "https://cdn.myanimelist.net/images/anime/1430/113075t.jpg",
        "large_image_url": "https://cdn.myanimelist.net/images/anime/1430/113075l.jpg"
      },
      "webp": {
        "image_url": "https://cdn.myanimelist.net/images/anime/1430/113075.webp",
        "small_image_url": "https://cdn.myanimelist.net/images/anime/1430/113075t.webp",
        "large_image_url": "https://cdn.myanimelist.net/images/anime/1430/113075l.webp"
      }
    },
    "trailer": {
      "youtube_id": null,
      "url": null,
      "embed_url": null,
      "images": {
        "image_url": null,
        "small_image_url": null,
        "medium_image_url": null,
        "large_image_url": null,
        "maximum_image_url": null
      }
    },
    "approved": true,
    "titles": [
      {
        "type": "Default",
        "title": "Otome Juurin Yuugi: Maiden Infringement Play"
      },
      {
        "type": "Japanese",
        "title": "乙女蹂躙遊戯～Maiden Infringement Play～"
      }
    ],
    "title": "Otome Juurin Yuugi: Maiden Infringement Play",
    "title_english": null,
    "title_japanese": "乙女蹂躙遊戯～Maiden Infringement Play～",
    "title_synonyms": [],
    "type": "OVA",
    "source": "Visual novel",
    "episodes": 2,
    "status": "Finished Airing",
    "airing": false,
    "aired": {
      "from": "2010-08-27T00:00:00+00:00",
      "to": "2010-11-26T00:00:00+00:00",
      "prop": {
        "from": {
          "day": 27,
          "month": 8,
          "year": 2010
        },
        "to": {
          "day": 26,
          "month": 11,
          "year": 2010
        }
      },
      "string": "Aug 27, 2010 to Nov 26, 2010"
    },
    "duration": "29 min per ep",
    "rating": "Rx - Hentai",
    "score": 6.22,
    "scored_by": 1734,
    "rank": null,
    "popularity": 8366,
    "members": 5818,
    "favorites": 17,
    "synopsis": "Kurata Ibuki and Miyauchi Akira are two very attractive virgin girls. Happily thinking they just won a prize at a summer resort for week, turns out to be a trick from some upper-class students at their school. The mastermind behind this whole \"abduction\" now have a whole week to train them to sex slaves. Will he successfully turn them to the dark side or will they struggle to the end and prevail?",
    "background": "",
    "season": null,
    "year": null,
    "broadcast": {
      "day": null,
      "time": null,
      "timezone": null,
      "string": null
    },
    "producers": [],
    "licensors": [],
    "studios": [
      {
        "mal_id": 274,
        "type": "anime",
        "name": "Suzuki Mirano",
        "url": "https://myanimelist.net/anime/producer/274/Suzuki_Mirano"
      }
    ],
    "genres": [
      {
        "mal_id": 12,
        "type": "anime",
        "name": "Hentai",
        "url": "https://myanimelist.net/anime/genre/12/Hentai"
      }
    ],
    "explicit_genres": [],
    "themes": [],
    "demographics": [],
    "relations": [],
    "theme": {
      "openings": [],
      "endings": []
    },
    "external": [
      {
        "name": "Official Site",
        "url": "http://www.guilty-soft.com/jyurinanime/index.html"
      },
      {
        "name": "AniDB",
        "url": "https://anidb.net/perl-bin/animedb.pl?show=anime&aid=7595"
      },
      {
        "name": "ANN",
        "url": "https://www.animenewsnetwork.com/encyclopedia/anime.php?id=11610"
      }
    ],
    "streaming": []
  }
}